pykov/Fetch.py
pykov/Harvester.py
pykov/Server.py
pykov/__init__.py
pykov/auth.py
pykov/constants.py
pykov/example.py
pykov/hwid.py
pykov/tarkov.py
pykov_eft-0.0.5.dist-info/METADATA
pykov_eft-0.0.5.dist-info/WHEEL
pykov_eft-0.0.5.dist-info/top_level.txt
pykov_eft-0.0.5.dist-info/RECORD
