Metadata-Version: 2.1
Name: pykov-eft
Version: 0.0.5
Summary: A Python API for Escape From Tarkov
Home-page: https://github.com/Xpheriono/pykov
Author: Xpheriono
Author-email: 
License: UNKNOWN
Platform: UNKNOWN
Classifier: Programming Language :: Python :: 3
Classifier: License :: OSI Approved :: MIT License
Classifier: Operating System :: OS Independent
Requires-Python: >=3.6
Requires-Dist: Flask
Requires-Dist: selenium
